MANIFEST.in
setup.py
ohbm/__init__.py
ohbm/abstracts.py
ohbm/api.py
ohbm/attendees.py
ohbm/auth.py
ohbm/categories.py
ohbm/events.py
ohbm/exhibitor.py
ohbm/planner.py
ohbm/roomset.py
ohbm/scripts.py
ohbm/settings.py
ohbm/system.py
ohbm/utils.py
ohbm.egg-info/PKG-INFO
ohbm.egg-info/SOURCES.txt
ohbm.egg-info/dependency_links.txt
ohbm.egg-info/not-zip-safe
ohbm.egg-info/pbr.json
ohbm.egg-info/requires.txt
ohbm.egg-info/top_level.txt
ohbm/script/__init__.py
ohbm/script/post_install.py